funasr_client/__init__.py
funasr_client/audio.py
funasr_client/callbacks.py
funasr_client/cli.py
funasr_client/client.py
funasr_client/config.py
funasr_client/connection.py
funasr_client/errors.py
funasr_client/models.py
funasr_client/protocols.py
funasr_client/utils.py
funasr_python-0.1.0.dist-info/METADATA
funasr_python-0.1.0.dist-info/WHEEL
funasr_python-0.1.0.dist-info/entry_points.txt
funasr_python-0.1.0.dist-info/licenses/LICENSE
funasr_python-0.1.0.dist-info/RECORD
