Metadata-Version: 2.4
Name: funasr-python
Version: 0.1.0
Summary: A high-performance Python client for FunASR WebSocket speech recognition service
Project-URL: Documentation, https://github.com/alibaba-damo-academy/FunASR
Project-URL: Repository, https://github.com/alibaba-damo-academy/FunASR
Project-URL: Changelog, https://github.com/alibaba-damo-academy/FunASR/blob/main/CHANGELOG.md
Project-URL: Bug Reports, https://github.com/alibaba-damo-academy/FunASR/issues
Author: FunASR Team
Maintainer: FunASR Team
License: MIT License
License-File: LICENSE
Keywords: asr,funasr,real-time,speech-recognition,streaming,websocket
Classifier: Development Status :: 4 - Beta
Classifier: Intended Audience :: Developers
Classifier: License :: OSI Approved :: MIT License
Classifier: Operating System :: OS Independent
Classifier: Programming Language :: Python :: 3
Classifier: Programming Language :: Python :: 3.8
Classifier: Programming Language :: Python :: 3.9
Classifier: Programming Language :: Python :: 3.10
Classifier: Programming Language :: Python :: 3.11
Classifier: Programming Language :: Python :: 3.12
Classifier: Topic :: Multimedia :: Sound/Audio :: Speech
Classifier: Topic :: Scientific/Engineering :: Artificial Intelligence
Classifier: Topic :: Software Development :: Libraries :: Python Modules
Requires-Python: >=3.8
Requires-Dist: aiofiles>=23.0.0
Requires-Dist: build>=1.2.2.post1
Requires-Dist: librosa>=0.9.0
Requires-Dist: numpy>=1.20.0
Requires-Dist: pydantic>=2.0.0
Requires-Dist: python-dotenv>=0.19.0
Requires-Dist: soundfile>=0.12.0
Requires-Dist: twine>=6.1.0
Requires-Dist: typing-extensions>=4.0.0; python_version < '3.11'
Requires-Dist: websockets>=11.0.0
Provides-Extra: all
Requires-Dist: coverage[toml]>=7.0.0; extra == 'all'
Requires-Dist: hatch>=1.7.0; extra == 'all'
Requires-Dist: mypy>=1.5.0; extra == 'all'
Requires-Dist: orjson>=3.8.0; extra == 'all'
Requires-Dist: pre-commit>=3.0.0; extra == 'all'
Requires-Dist: pyaudio>=0.2.11; extra == 'all'
Requires-Dist: pytest-asyncio>=0.21.0; extra == 'all'
Requires-Dist: pytest-cov>=4.0.0; extra == 'all'
Requires-Dist: pytest-mock>=3.10.0; extra == 'all'
Requires-Dist: pytest-timeout>=2.1.0; extra == 'all'
Requires-Dist: pytest>=7.0.0; extra == 'all'
Requires-Dist: ruff>=0.1.0; extra == 'all'
Requires-Dist: types-setuptools; extra == 'all'
Requires-Dist: uvloop>=0.17.0; (sys_platform != 'win32') and extra == 'all'
Requires-Dist: webrtcvad>=2.0.10; extra == 'all'
Provides-Extra: audio
Requires-Dist: pyaudio>=0.2.11; extra == 'audio'
Requires-Dist: webrtcvad>=2.0.10; extra == 'audio'
Provides-Extra: dev
Requires-Dist: coverage[toml]>=7.0.0; extra == 'dev'
Requires-Dist: hatch>=1.7.0; extra == 'dev'
Requires-Dist: mypy>=1.5.0; extra == 'dev'
Requires-Dist: orjson>=3.8.0; extra == 'dev'
Requires-Dist: pre-commit>=3.0.0; extra == 'dev'
Requires-Dist: pyaudio>=0.2.11; extra == 'dev'
Requires-Dist: pytest-asyncio>=0.21.0; extra == 'dev'
Requires-Dist: pytest-cov>=4.0.0; extra == 'dev'
Requires-Dist: pytest-mock>=3.10.0; extra == 'dev'
Requires-Dist: pytest-timeout>=2.1.0; extra == 'dev'
Requires-Dist: pytest>=7.0.0; extra == 'dev'
Requires-Dist: ruff>=0.1.0; extra == 'dev'
Requires-Dist: types-setuptools; extra == 'dev'
Requires-Dist: uvloop>=0.17.0; (sys_platform != 'win32') and extra == 'dev'
Requires-Dist: webrtcvad>=2.0.10; extra == 'dev'
Provides-Extra: lint
Requires-Dist: mypy>=1.5.0; extra == 'lint'
Requires-Dist: ruff>=0.1.0; extra == 'lint'
Requires-Dist: types-setuptools; extra == 'lint'
Provides-Extra: performance
Requires-Dist: orjson>=3.8.0; extra == 'performance'
Requires-Dist: uvloop>=0.17.0; (sys_platform != 'win32') and extra == 'performance'
Provides-Extra: test
Requires-Dist: coverage[toml]>=7.0.0; extra == 'test'
Requires-Dist: pytest-asyncio>=0.21.0; extra == 'test'
Requires-Dist: pytest-cov>=4.0.0; extra == 'test'
Requires-Dist: pytest-mock>=3.10.0; extra == 'test'
Requires-Dist: pytest-timeout>=2.1.0; extra == 'test'
Requires-Dist: pytest>=7.0.0; extra == 'test'
